aisafe_xgboost/__init__.py
aisafe_xgboost/inference.py
aisafe_xgboost/training.py
aisafe_xgboost/utils.py
aisafe_xgboost/videos.py
aisafe_xgboost/growth/height_female.csv
aisafe_xgboost/growth/height_male.csv
aisafe_xgboost/growth/weight_female.csv
aisafe_xgboost/growth/weight_male.csv
aisafe_xgboost/mock_data/basic_info.csv
aisafe_xgboost/mock_data/bruise.csv
aisafe_xgboost/mock_data/combined.csv
aisafe_xgboost/mock_data/emotion.csv
aisafe_xgboost/mock_data/exam.csv
aisafe_xgboost/mock_data/fracture.csv
aisafe_xgboost/mock_data/lab.csv
aisafe_xgboost/mock_data/true_label.csv
aisafe_xgboost/models/model_bruise.ubj
aisafe_xgboost/models/model_info.ubj
aisafe_xgboost/models/model_lab.ubj
aisafe_xgboost/models/model_response.ubj
aisafe_xgboost/models/model_video.ubj
aisafe_xgboost/models/model_xray.ubj
aisafe_xgboost/models/optimal_weights.npy
aisafe_xgboost-0.1.1.dist-info/LICENSE
aisafe_xgboost-0.1.1.dist-info/METADATA
aisafe_xgboost-0.1.1.dist-info/WHEEL
aisafe_xgboost-0.1.1.dist-info/entry_points.txt
aisafe_xgboost-0.1.1.dist-info/top_level.txt
aisafe_xgboost-0.1.1.dist-info/RECORD
