Metadata-Version: 2.1
Name: aisafe_xgboost
Version: 0.1.1
Summary: An ensemble xgboost model made by bright-rookie.
License: MIT License
Project-URL: repository, https://github.com/bright-rookie/aisafe_back
Keywords: child abuse,gradient boosting machine
Classifier: Development Status :: 3 - Alpha
Classifier: Environment :: Web Environment
Classifier: Intended Audience :: Healthcare Industry
Classifier: Intended Audience :: Science/Research
Classifier: Operating System :: POSIX
Classifier: Programming Language :: Python :: 3 :: Only
Classifier: Topic :: Scientific/Engineering :: Medical Science Apps.
Requires-Python: >=3.10
License-File: LICENSE
Requires-Dist: pandas>=2.2.0
Requires-Dist: xgboost>=2.0.0
Requires-Dist: scikit-learn>=1.3.0
Requires-Dist: numpy<2.0.0
Requires-Dist: scipy>=1.13.1
